glacier_upload/__init__.py
glacier_upload/archives.py
glacier_upload/cli.py
glacier_upload/inventories.py
glacier_upload/upload.py
glacier_upload/utils/tree_hash.py
glacier_upload-2.1.2.dist-info/METADATA
glacier_upload-2.1.2.dist-info/WHEEL
glacier_upload-2.1.2.dist-info/entry_points.txt
glacier_upload-2.1.2.dist-info/licenses/LICENSE
glacier_upload-2.1.2.dist-info/RECORD
