Metadata-Version: 2.4
Name: glacier-upload
Version: 2.1.2
Summary: A helper tool to upload and manage archives in AWS Glacier Vaults
License: GPL-3.0+
License-File: LICENSE
Keywords: AWS,glacier,upload,multipart
Author: Trapsilo Bumi
Author-email: tbumi@thpd.io
Requires-Python: >=3.9,<4.0
Classifier: Development Status :: 5 - Production/Stable
Classifier: Environment :: Console
Classifier: Intended Audience :: End Users/Desktop
Classifier: Intended Audience :: Information Technology
Classifier: Intended Audience :: System Administrators
Classifier: License :: OSI Approved :: GNU General Public License v3 or later (GPLv3+)
Classifier: Operating System :: OS Independent
Classifier: Programming Language :: Python :: 3
Classifier: Programming Language :: Python :: 3.9
Classifier: Programming Language :: Python :: 3.10
Classifier: Programming Language :: Python :: 3.11
Classifier: Programming Language :: Python :: 3.12
Classifier: Programming Language :: Python :: 3.13
Classifier: Programming Language :: Python :: 3.14
Classifier: Topic :: System :: Archiving
Classifier: Topic :: System :: Archiving :: Backup
Classifier: Topic :: System :: Archiving :: Compression
Requires-Dist: boto3 (>=1.34.113,<2.0.0)
Requires-Dist: click (>=8.1.7,<9.0.0)
Requires-Dist: tqdm (>=4.66.4,<5.0.0)
Project-URL: Repository, https://github.com/tbumi/glacier-upload
